<?xml version="1.0" encoding="UTF-8"?>
<beans xmlns="http://www.springframework.org/schema/beans"
	xmlns:xsi="http://www.w3.org/2001/XMLSchema-instance" 
	xmlns:util="http://www.springframework.org/schema/util"
	xsi:schemaLocation="
		http://www.springframework.org/schema/beans
		http://www.springframework.org/schema/beans/spring-beans.xsd
		http://www.springframework.org/schema/util
		http://www.springframework.org/schema/util/spring-util.xsd">
		
	<bean name="embeddedDatabasePopulator" class="org.springframework.jdbc.datasource.init.ResourceDatabasePopulator">
		<property name="scripts">
			<list>
				<value>classpath:database/DDL.sql</value>
				<value>classpath:database/DML.sql</value>
			</list>
		</property>
	</bean>
	
	<!-- Embedded Database -->
	<!-- by Default is HSQLDB -->
	<bean name="embeddedDS" class="org.springframework.jdbc.datasource.embedded.EmbeddedDatabaseFactoryBean">
		<property name="databasePopulator" ref="embeddedDatabasePopulator"/>
	</bean>
		
</beans>